cookiecache/__init__.py
cookiecache/__main__.py
cookiecache/cookiecache.py
cookiecache-1.2.dist-info/METADATA
cookiecache-1.2.dist-info/WHEEL
cookiecache-1.2.dist-info/entry_points.txt
cookiecache-1.2.dist-info/top_level.txt
cookiecache-1.2.dist-info/RECORD
