Metadata-Version: 2.1
Name: cookiecache
Version: 1.2
Summary: Simplify getting and storing cookies from the browser to use in Python
Home-page: https://github.com/pathtofile/cookiecache
Author: PatH
Author-email: pypi_cookiecache@tofile.dev
License: MIT
Platform: UNKNOWN
Classifier: Programming Language :: Python :: 3.8
Classifier: Operating System :: OS Independent
Requires-Python: >=3.8
Requires-Dist: browser-cookie3
